{
  "pedidos": [
    {
      "id": 1,
      "nome": "João Neto Barbosa",
      "cpf": "123.456.789.01",
      "descricao": "Um pedido com vários itens",
      "status": {
        "id": "novo"
      }
    },
    {
      "id": 2,
      "nome": "Zé pequeno",
      "cpf": "345.678.901.24",
      "descricao": "Uma pequena descrição de pedido",
      "status": {
        "id": "preparado"
      }
    },
    {
      "id": 3,
      "nome": "Zé pequeno",
      "cpf": "345.678.901.24",
      "descricao": "Uma pequena descrição de pedido",
      "status": {
        "id": "conferencia"
      }
    },
    {
      "id": 4,
      "nome": "Zé pequeno",
      "cpf": "345.678.901.24",
      "descricao": "Uma pequena descrição de pedido",
      "status": {
        "id": "pronto"
      }
    },
    {
      "id": 5,
      "nome": "Zé pequeno",
      "cpf": "345.678.901.24",
      "descricao": "Uma pequena descrição de pedido",
      "status": {
        "id": "excluido"
      }
    },
    {
      "id": 6,
      "nome": "Zé pequeno",
      "cpf": "345.678.901.24",
      "descricao": "Uma pequena descrição de pedido",
      "status": {
        "id": "pagamento"
      }
    }
  ],
  "status": [
    {
      "id": "novo",
      "descricao": "NOVO"
    },
    {
      "id": "preparado",
      "descricao": "PREPARANDO"
    },
    {
      "id": "conferencia",
      "descricao": "CONFERÊNCIA"
    },
    {
      "id": "pronto",
      "descricao": "PRONTO"
    },
    {
      "id": "excluido",
      "descricao": "EXCLUÍDO"
    },
    {
      "id": "pagamento",
      "descricao": "PAGO"
    }
  ]
}